oarepo_validate/__init__.py
oarepo_validate/cli.py
oarepo_validate/config.py
oarepo_validate/ext.py
oarepo_validate/loaders.py
oarepo_validate/marshmallow.py
oarepo_validate/proxies.py
oarepo_validate/record.py
oarepo_validate/serializers.py
oarepo_validate/signals.py
oarepo_validate/utils.py
oarepo_validate/version.py
oarepo_validate-1.5.5.dist-info/AUTHORS.rst
oarepo_validate-1.5.5.dist-info/LICENSE
oarepo_validate-1.5.5.dist-info/METADATA
oarepo_validate-1.5.5.dist-info/WHEEL
oarepo_validate-1.5.5.dist-info/entry_points.txt
oarepo_validate-1.5.5.dist-info/top_level.txt
oarepo_validate-1.5.5.dist-info/RECORD
