Metadata-Version: 2.1
Name: oarepo-validate
Version: 1.5.5
Summary: OArepo Validate library for record metadata validation
Home-page: https://github.com/oarepo/oarepo-validate
Author: UCT Prague
Author-email: miroslav.simek@vscht.cz
License: MIT
Keywords: metadata validation oarepo records
Platform: any
Classifier: Environment :: Web Environment
Classifier: Intended Audience :: Developers
Classifier: License :: OSI Approved :: MIT License
Classifier: Operating System :: OS Independent
Classifier: Programming Language :: Python
Classifier: Topic :: Internet :: WWW/HTTP :: Dynamic Content
Classifier: Topic :: Software Development :: Libraries :: Python Modules
Classifier: Programming Language :: Python :: 3
Classifier: Programming Language :: Python :: 3.8
Classifier: Development Status :: 4 - Beta
License-File: LICENSE
License-File: AUTHORS.rst
Requires-Dist: wrapt (>=1.11.2)
Provides-Extra: dev
Requires-Dist: oarepo[tests] (~=3.3.0) ; extra == 'dev'
Requires-Dist: invenio-app ; extra == 'dev'
Requires-Dist: redis ; extra == 'dev'
Requires-Dist: markdown-toc ; extra == 'dev'
Provides-Extra: tests
Requires-Dist: oarepo[tests] (~=3.3.0) ; extra == 'tests'
